{
	"textures": [
		{
			"image": "playerAtlas.png",
			"format": "RGBA8888",
			"size": {
				"w": 512,
				"h": 512
			},
			"scale": 1,
			"frames": [
				{
					"filename": "adventurer-bow-Sheet",
					"rotated": false,
					"trimmed": true,
					"sourceSize": {
						"w": 200,
						"h": 148
					},
					"spriteSourceSize": {
						"x": 11,
						"y": 10,
						"w": 186,
						"h": 134
					},
					"frame": {
						"x": 1,
						"y": 1,
						"w": 186,
						"h": 134
					}
				},
				{
					"filename": "adventurer-air-attack-3-end-00",
					"rotated": false,
					"trimmed": true,
					"sourceSize": {
						"w": 50,
						"h": 37
					},
					"spriteSourceSize": {
						"x": 1,
						"y": 0,
						"w": 48,
						"h": 36
					},
					"frame": {
						"x": 1,
						"y": 137,
						"w": 48,
						"h": 36
					}
				},
				{
					"filename": "adventurer-attack3-02",
					"rotated": false,
					"trimmed": true,
					"sourceSize": {
						"w": 50,
						"h": 37
					},
					"spriteSourceSize": {
						"x": 2,
						"y": 13,
						"w": 48,
						"h": 23
					},
					"frame": {
						"x": 51,
						"y": 137,
						"w": 48,
						"h": 23
					}
				},
				{
					"filename": "adventurer-air-attack1-01",
					"rotated": false,
					"trimmed": true,
					"sourceSize": {
						"w": 50,
						"h": 37
					},
					"spriteSourceSize": {
						"x": 2,
						"y": 4,
						"w": 46,
						"h": 30
					},
					"frame": {
						"x": 101,
						"y": 137,
						"w": 46,
						"h": 30
					}
				},
				{
					"filename": "adventurer-air-attack-3-end-01",
					"rotated": false,
					"trimmed": true,
					"sourceSize": {
						"w": 50,
						"h": 37
					},
					"spriteSourceSize": {
						"x": 3,
						"y": 6,
						"w": 46,
						"h": 30
					},
					"frame": {
						"x": 1,
						"y": 175,
						"w": 46,
						"h": 30
					}
				},
				{
					"filename": "adventurer-air-attack-3-end-02",
					"rotated": false,
					"trimmed": true,
					"sourceSize": {
						"w": 50,
						"h": 37
					},
					"spriteSourceSize": {
						"x": 2,
						"y": 14,
						"w": 46,
						"h": 22
					},
					"frame": {
						"x": 51,
						"y": 162,
						"w": 46,
						"h": 22
					}
				},
				{
					"filename": "adventurer-attack2-03",
					"rotated": false,
					"trimmed": true,
					"sourceSize": {
						"w": 50,
						"h": 37
					},
					"spriteSourceSize": {
						"x": 10,
						"y": 7,
						"w": 37,
						"h": 29
					},
					"frame": {
						"x": 149,
						"y": 137,
						"w": 37,
						"h": 29
					}
				},
				{
					"filename": "adventurer-bow-07",
					"rotated": false,
					"trimmed": true,
					"sourceSize": {
						"w": 50,
						"h": 37
					},
					"spriteSourceSize": {
						"x": 11,
						"y": 10,
						"w": 36,
						"h": 26
					},
					"frame": {
						"x": 149,
						"y": 168,
						"w": 36,
						"h": 26
					}
				},
				{
					"filename": "adventurer-attack1-02",
					"rotated": false,
					"trimmed": true,
					"sourceSize": {
						"w": 50,
						"h": 37
					},
					"spriteSourceSize": {
						"x": 15,
						"y": 0,
						"w": 34,
						"h": 36
					},
					"frame": {
						"x": 99,
						"y": 169,
						"w": 34,
						"h": 36
					}
				},
				{
					"filename": "adventurer-attack1-03",
					"rotated": false,
					"trimmed": true,
					"sourceSize": {
						"w": 50,
						"h": 37
					},
					"spriteSourceSize": {
						"x": 15,
						"y": 0,
						"w": 27,
						"h": 36
					},
					"frame": {
						"x": 189,
						"y": 1,
						"w": 27,
						"h": 36
					}
				},
				{
					"filename": "adventurer-bow-jump-04",
					"rotated": false,
					"trimmed": true,
					"sourceSize": {
						"w": 50,
						"h": 37
					},
					"spriteSourceSize": {
						"x": 11,
						"y": 7,
						"w": 36,
						"h": 26
					},
					"frame": {
						"x": 1,
						"y": 207,
						"w": 36,
						"h": 26
					}
				},
				{
					"filename": "adventurer-bow-jump-05",
					"rotated": false,
					"trimmed": true,
					"sourceSize": {
						"w": 50,
						"h": 37
					},
					"spriteSourceSize": {
						"x": 10,
						"y": 7,
						"w": 34,
						"h": 26
					},
					"frame": {
						"x": 39,
						"y": 207,
						"w": 34,
						"h": 26
					}
				},
				{
					"filename": "adventurer-stand-00",
					"rotated": false,
					"trimmed": true,
					"sourceSize": {
						"w": 50,
						"h": 37
					},
					"spriteSourceSize": {
						"x": 5,
						"y": 20,
						"w": 34,
						"h": 16
					},
					"frame": {
						"x": 49,
						"y": 186,
						"w": 34,
						"h": 16
					}
				},
				{
					"filename": "adventurer-air-attack2-00",
					"rotated": false,
					"trimmed": true,
					"sourceSize": {
						"w": 50,
						"h": 37
					},
					"spriteSourceSize": {
						"x": 15,
						"y": 4,
						"w": 34,
						"h": 31
					},
					"frame": {
						"x": 135,
						"y": 196,
						"w": 34,
						"h": 31
					}
				},
				{
					"filename": "adventurer-crnr-grb-03",
					"rotated": false,
					"trimmed": true,
					"sourceSize": {
						"w": 50,
						"h": 37
					},
					"spriteSourceSize": {
						"x": 21,
						"y": 3,
						"w": 14,
						"h": 34
					},
					"frame": {
						"x": 171,
						"y": 196,
						"w": 14,
						"h": 34
					}
				},
				{
					"filename": "adventurer-crnr-grb-02",
					"rotated": false,
					"trimmed": true,
					"sourceSize": {
						"w": 50,
						"h": 37
					},
					"spriteSourceSize": {
						"x": 20,
						"y": 3,
						"w": 15,
						"h": 34
					},
					"frame": {
						"x": 189,
						"y": 39,
						"w": 15,
						"h": 34
					}
				},
				{
					"filename": "adventurer-slide-01",
					"rotated": false,
					"trimmed": true,
					"sourceSize": {
						"w": 50,
						"h": 37
					},
					"spriteSourceSize": {
						"x": 5,
						"y": 21,
						"w": 34,
						"h": 15
					},
					"frame": {
						"x": 75,
						"y": 207,
						"w": 34,
						"h": 15
					}
				},
				{
					"filename": "adventurer-crnr-grb-01",
					"rotated": false,
					"trimmed": true,
					"sourceSize": {
						"w": 50,
						"h": 37
					},
					"spriteSourceSize": {
						"x": 21,
						"y": 3,
						"w": 14,
						"h": 34
					},
					"frame": {
						"x": 189,
						"y": 75,
						"w": 14,
						"h": 34
					}
				},
				{
					"filename": "adventurer-crnr-grb-00",
					"rotated": false,
					"trimmed": true,
					"sourceSize": {
						"w": 50,
						"h": 37
					},
					"spriteSourceSize": {
						"x": 21,
						"y": 3,
						"w": 14,
						"h": 34
					},
					"frame": {
						"x": 189,
						"y": 111,
						"w": 14,
						"h": 34
					}
				},
				{
					"filename": "adventurer-slide-00",
					"rotated": false,
					"trimmed": true,
					"sourceSize": {
						"w": 50,
						"h": 37
					},
					"spriteSourceSize": {
						"x": 5,
						"y": 21,
						"w": 34,
						"h": 15
					},
					"frame": {
						"x": 218,
						"y": 1,
						"w": 34,
						"h": 15
					}
				},
				{
					"filename": "adventurer-attack3-05",
					"rotated": false,
					"trimmed": true,
					"sourceSize": {
						"w": 50,
						"h": 37
					},
					"spriteSourceSize": {
						"x": 0,
						"y": 16,
						"w": 34,
						"h": 20
					},
					"frame": {
						"x": 218,
						"y": 18,
						"w": 34,
						"h": 20
					}
				},
				{
					"filename": "adventurer-attack3-04",
					"rotated": false,
					"trimmed": true,
					"sourceSize": {
						"w": 50,
						"h": 37
					},
					"spriteSourceSize": {
						"x": 0,
						"y": 16,
						"w": 34,
						"h": 20
					},
					"frame": {
						"x": 206,
						"y": 40,
						"w": 34,
						"h": 20
					}
				},
				{
					"filename": "adventurer-wall-slide-01",
					"rotated": false,
					"trimmed": true,
					"sourceSize": {
						"w": 50,
						"h": 37
					},
					"spriteSourceSize": {
						"x": 16,
						"y": 2,
						"w": 17,
						"h": 32
					},
					"frame": {
						"x": 206,
						"y": 62,
						"w": 17,
						"h": 32
					}
				},
				{
					"filename": "adventurer-attack1-04",
					"rotated": false,
					"trimmed": true,
					"sourceSize": {
						"w": 50,
						"h": 37
					},
					"spriteSourceSize": {
						"x": 15,
						"y": 4,
						"w": 19,
						"h": 32
					},
					"frame": {
						"x": 225,
						"y": 62,
						"w": 19,
						"h": 32
					}
				},
				{
					"filename": "adventurer-attack2-04",
					"rotated": false,
					"trimmed": true,
					"sourceSize": {
						"w": 50,
						"h": 37
					},
					"spriteSourceSize": {
						"x": 2,
						"y": 15,
						"w": 32,
						"h": 21
					},
					"frame": {
						"x": 205,
						"y": 96,
						"w": 32,
						"h": 21
					}
				},
				{
					"filename": "adventurer-air-attack3-loop-01",
					"rotated": false,
					"trimmed": true,
					"sourceSize": {
						"w": 50,
						"h": 37
					},
					"spriteSourceSize": {
						"x": 8,
						"y": 2,
						"w": 27,
						"h": 31
					},
					"frame": {
						"x": 205,
						"y": 119,
						"w": 27,
						"h": 31
					}
				},
				{
					"filename": "adventurer-attack3-03",
					"rotated": false,
					"trimmed": true,
					"sourceSize": {
						"w": 50,
						"h": 37
					},
					"spriteSourceSize": {
						"x": 3,
						"y": 17,
						"w": 31,
						"h": 19
					},
					"frame": {
						"x": 188,
						"y": 152,
						"w": 31,
						"h": 19
					}
				},
				{
					"filename": "adventurer-air-attack3-rdy-00",
					"rotated": false,
					"trimmed": true,
					"sourceSize": {
						"w": 50,
						"h": 37
					},
					"spriteSourceSize": {
						"x": 8,
						"y": 1,
						"w": 28,
						"h": 31
					},
					"frame": {
						"x": 221,
						"y": 152,
						"w": 28,
						"h": 31
					}
				},
				{
					"filename": "adventurer-fall-00",
					"rotated": false,
					"trimmed": true,
					"sourceSize": {
						"w": 50,
						"h": 37
					},
					"spriteSourceSize": {
						"x": 18,
						"y": 1,
						"w": 17,
						"h": 31
					},
					"frame": {
						"x": 234,
						"y": 119,
						"w": 17,
						"h": 31
					}
				},
				{
					"filename": "adventurer-wall-slide-00",
					"rotated": false,
					"trimmed": true,
					"sourceSize": {
						"w": 50,
						"h": 37
					},
					"spriteSourceSize": {
						"x": 16,
						"y": 3,
						"w": 17,
						"h": 31
					},
					"frame": {
						"x": 187,
						"y": 173,
						"w": 17,
						"h": 31
					}
				},
				{
					"filename": "adventurer-air-attack1-03",
					"rotated": false,
					"trimmed": true,
					"sourceSize": {
						"w": 50,
						"h": 37
					},
					"spriteSourceSize": {
						"x": 5,
						"y": 2,
						"w": 27,
						"h": 31
					},
					"frame": {
						"x": 206,
						"y": 185,
						"w": 27,
						"h": 31
					}
				},
				{
					"filename": "adventurer-attack2-05",
					"rotated": false,
					"trimmed": true,
					"sourceSize": {
						"w": 50,
						"h": 37
					},
					"spriteSourceSize": {
						"x": 2,
						"y": 14,
						"w": 31,
						"h": 22
					},
					"frame": {
						"x": 1,
						"y": 235,
						"w": 31,
						"h": 22
					}
				},
				{
					"filename": "adventurer-air-attack2-01",
					"rotated": false,
					"trimmed": true,
					"sourceSize": {
						"w": 50,
						"h": 37
					},
					"spriteSourceSize": {
						"x": 16,
						"y": 3,
						"w": 23,
						"h": 31
					},
					"frame": {
						"x": 75,
						"y": 224,
						"w": 23,
						"h": 31
					}
				},
				{
					"filename": "adventurer-stand-01",
					"rotated": false,
					"trimmed": true,
					"sourceSize": {
						"w": 50,
						"h": 37
					},
					"spriteSourceSize": {
						"x": 9,
						"y": 19,
						"w": 30,
						"h": 17
					},
					"frame": {
						"x": 100,
						"y": 224,
						"w": 30,
						"h": 17
					}
				},
				{
					"filename": "adventurer-air-attack1-02",
					"rotated": false,
					"trimmed": true,
					"sourceSize": {
						"w": 50,
						"h": 37
					},
					"spriteSourceSize": {
						"x": 6,
						"y": 3,
						"w": 29,
						"h": 30
					},
					"frame": {
						"x": 187,
						"y": 218,
						"w": 29,
						"h": 30
					}
				},
				{
					"filename": "adventurer-fall-01",
					"rotated": false,
					"trimmed": true,
					"sourceSize": {
						"w": 50,
						"h": 37
					},
					"spriteSourceSize": {
						"x": 18,
						"y": 2,
						"w": 17,
						"h": 30
					},
					"frame": {
						"x": 235,
						"y": 185,
						"w": 17,
						"h": 30
					}
				},
				{
					"filename": "adventurer-idle-01",
					"rotated": false,
					"trimmed": true,
					"sourceSize": {
						"w": 50,
						"h": 37
					},
					"spriteSourceSize": {
						"x": 16,
						"y": 6,
						"w": 17,
						"h": 30
					},
					"frame": {
						"x": 235,
						"y": 217,
						"w": 17,
						"h": 30
					}
				},
				{
					"filename": "adventurer-idle-02",
					"rotated": false,
					"trimmed": true,
					"sourceSize": {
						"w": 50,
						"h": 37
					},
					"spriteSourceSize": {
						"x": 15,
						"y": 6,
						"w": 19,
						"h": 30
					},
					"frame": {
						"x": 254,
						"y": 1,
						"w": 19,
						"h": 30
					}
				},
				{
					"filename": "adventurer-air-attack3-loop-00",
					"rotated": false,
					"trimmed": true,
					"sourceSize": {
						"w": 50,
						"h": 37
					},
					"spriteSourceSize": {
						"x": 8,
						"y": 3,
						"w": 27,
						"h": 30
					},
					"frame": {
						"x": 246,
						"y": 40,
						"w": 27,
						"h": 30
					}
				},
				{
					"filename": "adventurer-ladder-climb-00",
					"rotated": false,
					"trimmed": true,
					"sourceSize": {
						"w": 50,
						"h": 37
					},
					"spriteSourceSize": {
						"x": 19,
						"y": 4,
						"w": 13,
						"h": 30
					},
					"frame": {
						"x": 251,
						"y": 152,
						"w": 13,
						"h": 30
					}
				},
				{
					"filename": "adventurer-ladder-climb-02",
					"rotated": false,
					"trimmed": true,
					"sourceSize": {
						"w": 50,
						"h": 37
					},
					"spriteSourceSize": {
						"x": 19,
						"y": 4,
						"w": 13,
						"h": 30
					},
					"frame": {
						"x": 218,
						"y": 218,
						"w": 13,
						"h": 30
					}
				},
				{
					"filename": "adventurer-cast-loop-01",
					"rotated": false,
					"trimmed": true,
					"sourceSize": {
						"w": 50,
						"h": 37
					},
					"spriteSourceSize": {
						"x": 13,
						"y": 12,
						"w": 29,
						"h": 24
					},
					"frame": {
						"x": 132,
						"y": 232,
						"w": 29,
						"h": 24
					}
				},
				{
					"filename": "adventurer-idle-00",
					"rotated": false,
					"trimmed": true,
					"sourceSize": {
						"w": 50,
						"h": 37
					},
					"spriteSourceSize": {
						"x": 14,
						"y": 7,
						"w": 19,
						"h": 29
					},
					"frame": {
						"x": 254,
						"y": 184,
						"w": 19,
						"h": 29
					}
				},
				{
					"filename": "adventurer-crnr-clmb-00",
					"rotated": false,
					"trimmed": true,
					"sourceSize": {
						"w": 50,
						"h": 37
					},
					"spriteSourceSize": {
						"x": 21,
						"y": 6,
						"w": 16,
						"h": 29
					},
					"frame": {
						"x": 254,
						"y": 215,
						"w": 16,
						"h": 29
					}
				},
				{
					"filename": "adventurer-cast-loop-03",
					"rotated": false,
					"trimmed": true,
					"sourceSize": {
						"w": 50,
						"h": 37
					},
					"spriteSourceSize": {
						"x": 13,
						"y": 12,
						"w": 29,
						"h": 24
					},
					"frame": {
						"x": 1,
						"y": 259,
						"w": 29,
						"h": 24
					}
				},
				{
					"filename": "adventurer-crnr-jmp-00",
					"rotated": false,
					"trimmed": true,
					"sourceSize": {
						"w": 50,
						"h": 37
					},
					"spriteSourceSize": {
						"x": 17,
						"y": 7,
						"w": 23,
						"h": 29
					},
					"frame": {
						"x": 246,
						"y": 72,
						"w": 23,
						"h": 29
					}
				},
				{
					"filename": "adventurer-swrd-shte-01",
					"rotated": false,
					"trimmed": true,
					"sourceSize": {
						"w": 50,
						"h": 37
					},
					"spriteSourceSize": {
						"x": 13,
						"y": 7,
						"w": 19,
						"h": 29
					},
					"frame": {
						"x": 254,
						"y": 246,
						"w": 19,
						"h": 29
					}
				},
				{
					"filename": "adventurer-swrd-drw-02",
					"rotated": false,
					"trimmed": true,
					"sourceSize": {
						"w": 50,
						"h": 37
					},
					"spriteSourceSize": {
						"x": 13,
						"y": 7,
						"w": 19,
						"h": 29
					},
					"frame": {
						"x": 233,
						"y": 249,
						"w": 19,
						"h": 29
					}
				},
				{
					"filename": "adventurer-swrd-shte-00",
					"rotated": false,
					"trimmed": true,
					"sourceSize": {
						"w": 50,
						"h": 37
					},
					"spriteSourceSize": {
						"x": 8,
						"y": 7,
						"w": 24,
						"h": 29
					},
					"frame": {
						"x": 163,
						"y": 250,
						"w": 24,
						"h": 29
					}
				},
				{
					"filename": "adventurer-swrd-drw-03",
					"rotated": false,
					"trimmed": true,
					"sourceSize": {
						"w": 50,
						"h": 37
					},
					"spriteSourceSize": {
						"x": 8,
						"y": 7,
						"w": 24,
						"h": 29
					},
					"frame": {
						"x": 189,
						"y": 250,
						"w": 24,
						"h": 29
					}
				},
				{
					"filename": "adventurer-bow-08",
					"rotated": false,
					"trimmed": true,
					"sourceSize": {
						"w": 50,
						"h": 37
					},
					"spriteSourceSize": {
						"x": 15,
						"y": 10,
						"w": 29,
						"h": 26
					},
					"frame": {
						"x": 34,
						"y": 257,
						"w": 29,
						"h": 26
					}
				},
				{
					"filename": "adventurer-crnr-jmp-01",
					"rotated": false,
					"trimmed": true,
					"sourceSize": {
						"w": 50,
						"h": 37
					},
					"spriteSourceSize": {
						"x": 18,
						"y": 7,
						"w": 22,
						"h": 29
					},
					"frame": {
						"x": 100,
						"y": 243,
						"w": 22,
						"h": 29
					}
				},
				{
					"filename": "adventurer-idle-03",
					"rotated": false,
					"trimmed": true,
					"sourceSize": {
						"w": 50,
						"h": 37
					},
					"spriteSourceSize": {
						"x": 13,
						"y": 7,
						"w": 20,
						"h": 29
					},
					"frame": {
						"x": 253,
						"y": 103,
						"w": 20,
						"h": 29
					}
				},
				{
					"filename": "adventurer-run-00",
					"rotated": false,
					"trimmed": true,
					"sourceSize": {
						"w": 50,
						"h": 37
					},
					"spriteSourceSize": {
						"x": 17,
						"y": 8,
						"w": 20,
						"h": 28
					},
					"frame": {
						"x": 275,
						"y": 1,
						"w": 20,
						"h": 28
					}
				},
				{
					"filename": "adventurer-idle-2-03",
					"rotated": false,
					"trimmed": true,
					"sourceSize": {
						"w": 50,
						"h": 37
					},
					"spriteSourceSize": {
						"x": 9,
						"y": 8,
						"w": 25,
						"h": 28
					},
					"frame": {
						"x": 266,
						"y": 134,
						"w": 25,
						"h": 28
					}
				},
				{
					"filename": "adventurer-run-03",
					"rotated": false,
					"trimmed": true,
					"sourceSize": {
						"w": 50,
						"h": 37
					},
					"spriteSourceSize": {
						"x": 17,
						"y": 8,
						"w": 23,
						"h": 28
					},
					"frame": {
						"x": 272,
						"y": 215,
						"w": 23,
						"h": 28
					}
				},
				{
					"filename": "adventurer-idle-2-02",
					"rotated": false,
					"trimmed": true,
					"sourceSize": {
						"w": 50,
						"h": 37
					},
					"spriteSourceSize": {
						"x": 9,
						"y": 8,
						"w": 25,
						"h": 28
					},
					"frame": {
						"x": 1,
						"y": 285,
						"w": 25,
						"h": 28
					}
				},
				{
					"filename": "adventurer-attack2-02",
					"rotated": false,
					"trimmed": true,
					"sourceSize": {
						"w": 50,
						"h": 37
					},
					"spriteSourceSize": {
						"x": 13,
						"y": 9,
						"w": 20,
						"h": 27
					},
					"frame": {
						"x": 275,
						"y": 31,
						"w": 20,
						"h": 27
					}
				},
				{
					"filename": "adventurer-bow-jump-03",
					"rotated": false,
					"trimmed": true,
					"sourceSize": {
						"w": 50,
						"h": 37
					},
					"spriteSourceSize": {
						"x": 11,
						"y": 8,
						"w": 27,
						"h": 25
					},
					"frame": {
						"x": 28,
						"y": 285,
						"w": 27,
						"h": 25
					}
				},
				{
					"filename": "adventurer-ladder-climb-01",
					"rotated": false,
					"trimmed": true,
					"sourceSize": {
						"w": 50,
						"h": 37
					},
					"spriteSourceSize": {
						"x": 19,
						"y": 5,
						"w": 13,
						"h": 27
					},
					"frame": {
						"x": 57,
						"y": 285,
						"w": 13,
						"h": 27
					}
				},
				{
					"filename": "adventurer-idle-2-00",
					"rotated": false,
					"trimmed": true,
					"sourceSize": {
						"w": 50,
						"h": 37
					},
					"spriteSourceSize": {
						"x": 10,
						"y": 9,
						"w": 23,
						"h": 27
					},
					"frame": {
						"x": 271,
						"y": 72,
						"w": 23,
						"h": 27
					}
				},
				{
					"filename": "adventurer-ladder-climb-03",
					"rotated": false,
					"trimmed": true,
					"sourceSize": {
						"w": 50,
						"h": 37
					},
					"spriteSourceSize": {
						"x": 19,
						"y": 5,
						"w": 13,
						"h": 27
					},
					"frame": {
						"x": 215,
						"y": 250,
						"w": 13,
						"h": 27
					}
				},
				{
					"filename": "adventurer-attack2-01",
					"rotated": false,
					"trimmed": true,
					"sourceSize": {
						"w": 50,
						"h": 37
					},
					"spriteSourceSize": {
						"x": 15,
						"y": 9,
						"w": 18,
						"h": 27
					},
					"frame": {
						"x": 275,
						"y": 164,
						"w": 18,
						"h": 27
					}
				},
				{
					"filename": "adventurer-run-01",
					"rotated": false,
					"trimmed": true,
					"sourceSize": {
						"w": 50,
						"h": 37
					},
					"spriteSourceSize": {
						"x": 16,
						"y": 9,
						"w": 20,
						"h": 27
					},
					"frame": {
						"x": 275,
						"y": 245,
						"w": 20,
						"h": 27
					}
				},
				{
					"filename": "adventurer-cast-loop-00",
					"rotated": false,
					"trimmed": true,
					"sourceSize": {
						"w": 50,
						"h": 37
					},
					"spriteSourceSize": {
						"x": 15,
						"y": 12,
						"w": 27,
						"h": 24
					},
					"frame": {
						"x": 65,
						"y": 257,
						"w": 27,
						"h": 24
					}
				},
				{
					"filename": "adventurer-attack1-00",
					"rotated": false,
					"trimmed": true,
					"sourceSize": {
						"w": 50,
						"h": 37
					},
					"spriteSourceSize": {
						"x": 7,
						"y": 14,
						"w": 27,
						"h": 22
					},
					"frame": {
						"x": 72,
						"y": 283,
						"w": 27,
						"h": 22
					}
				},
				{
					"filename": "adventurer-run-04",
					"rotated": false,
					"trimmed": true,
					"sourceSize": {
						"w": 50,
						"h": 37
					},
					"spriteSourceSize": {
						"x": 16,
						"y": 9,
						"w": 20,
						"h": 27
					},
					"frame": {
						"x": 275,
						"y": 101,
						"w": 20,
						"h": 27
					}
				},
				{
					"filename": "adventurer-cast-loop-02",
					"rotated": false,
					"trimmed": true,
					"sourceSize": {
						"w": 50,
						"h": 37
					},
					"spriteSourceSize": {
						"x": 15,
						"y": 12,
						"w": 27,
						"h": 24
					},
					"frame": {
						"x": 101,
						"y": 281,
						"w": 27,
						"h": 24
					}
				},
				{
					"filename": "adventurer-cast-03",
					"rotated": false,
					"trimmed": true,
					"sourceSize": {
						"w": 50,
						"h": 37
					},
					"spriteSourceSize": {
						"x": 15,
						"y": 12,
						"w": 27,
						"h": 24
					},
					"frame": {
						"x": 130,
						"y": 258,
						"w": 27,
						"h": 24
					}
				},
				{
					"filename": "adventurer-jump-02",
					"rotated": false,
					"trimmed": true,
					"sourceSize": {
						"w": 50,
						"h": 37
					},
					"spriteSourceSize": {
						"x": 17,
						"y": 7,
						"w": 19,
						"h": 27
					},
					"frame": {
						"x": 275,
						"y": 274,
						"w": 19,
						"h": 27
					}
				},
				{
					"filename": "adventurer-idle-2-01",
					"rotated": false,
					"trimmed": true,
					"sourceSize": {
						"w": 50,
						"h": 37
					},
					"spriteSourceSize": {
						"x": 10,
						"y": 9,
						"w": 23,
						"h": 27
					},
					"frame": {
						"x": 130,
						"y": 284,
						"w": 23,
						"h": 27
					}
				},
				{
					"filename": "adventurer-attack2-00",
					"rotated": false,
					"trimmed": true,
					"sourceSize": {
						"w": 50,
						"h": 37
					},
					"spriteSourceSize": {
						"x": 15,
						"y": 10,
						"w": 18,
						"h": 26
					},
					"frame": {
						"x": 254,
						"y": 277,
						"w": 18,
						"h": 26
					}
				},
				{
					"filename": "adventurer-air-attack1-00",
					"rotated": false,
					"trimmed": true,
					"sourceSize": {
						"w": 50,
						"h": 37
					},
					"spriteSourceSize": {
						"x": 15,
						"y": 9,
						"w": 18,
						"h": 26
					},
					"frame": {
						"x": 155,
						"y": 284,
						"w": 18,
						"h": 26
					}
				},
				{
					"filename": "adventurer-cast-00",
					"rotated": false,
					"trimmed": true,
					"sourceSize": {
						"w": 50,
						"h": 37
					},
					"spriteSourceSize": {
						"x": 15,
						"y": 10,
						"w": 21,
						"h": 26
					},
					"frame": {
						"x": 175,
						"y": 281,
						"w": 21,
						"h": 26
					}
				},
				{
					"filename": "adventurer-attack3-00",
					"rotated": false,
					"trimmed": true,
					"sourceSize": {
						"w": 50,
						"h": 37
					},
					"spriteSourceSize": {
						"x": 19,
						"y": 10,
						"w": 20,
						"h": 26
					},
					"frame": {
						"x": 198,
						"y": 281,
						"w": 20,
						"h": 26
					}
				},
				{
					"filename": "adventurer-crnr-clmb-01",
					"rotated": false,
					"trimmed": true,
					"sourceSize": {
						"w": 50,
						"h": 37
					},
					"spriteSourceSize": {
						"x": 21,
						"y": 7,
						"w": 15,
						"h": 26
					},
					"frame": {
						"x": 220,
						"y": 280,
						"w": 15,
						"h": 26
					}
				},
				{
					"filename": "adventurer-items-02",
					"rotated": false,
					"trimmed": true,
					"sourceSize": {
						"w": 50,
						"h": 37
					},
					"spriteSourceSize": {
						"x": 15,
						"y": 10,
						"w": 19,
						"h": 26
					},
					"frame": {
						"x": 297,
						"y": 1,
						"w": 19,
						"h": 26
					}
				},
				{
					"filename": "adventurer-bow-06",
					"rotated": false,
					"trimmed": true,
					"sourceSize": {
						"w": 50,
						"h": 37
					},
					"spriteSourceSize": {
						"x": 14,
						"y": 10,
						"w": 24,
						"h": 26
					},
					"frame": {
						"x": 1,
						"y": 315,
						"w": 24,
						"h": 26
					}
				},
				{
					"filename": "adventurer-swrd-drw-01",
					"rotated": false,
					"trimmed": true,
					"sourceSize": {
						"w": 50,
						"h": 37
					},
					"spriteSourceSize": {
						"x": 15,
						"y": 10,
						"w": 18,
						"h": 26
					},
					"frame": {
						"x": 27,
						"y": 315,
						"w": 18,
						"h": 26
					}
				},
				{
					"filename": "adventurer-attack3-01",
					"rotated": false,
					"trimmed": true,
					"sourceSize": {
						"w": 50,
						"h": 37
					},
					"spriteSourceSize": {
						"x": 20,
						"y": 10,
						"w": 20,
						"h": 26
					},
					"frame": {
						"x": 296,
						"y": 60,
						"w": 20,
						"h": 26
					}
				},
				{
					"filename": "adventurer-swrd-shte-02",
					"rotated": false,
					"trimmed": true,
					"sourceSize": {
						"w": 50,
						"h": 37
					},
					"spriteSourceSize": {
						"x": 13,
						"y": 10,
						"w": 20,
						"h": 26
					},
					"frame": {
						"x": 296,
						"y": 274,
						"w": 20,
						"h": 26
					}
				},
				{
					"filename": "adventurer-bow-04",
					"rotated": false,
					"trimmed": true,
					"sourceSize": {
						"w": 50,
						"h": 37
					},
					"spriteSourceSize": {
						"x": 14,
						"y": 10,
						"w": 24,
						"h": 26
					},
					"frame": {
						"x": 47,
						"y": 314,
						"w": 24,
						"h": 26
					}
				},
				{
					"filename": "adventurer-air-attack2-02",
					"rotated": false,
					"trimmed": true,
					"sourceSize": {
						"w": 50,
						"h": 37
					},
					"spriteSourceSize": {
						"x": 15,
						"y": 7,
						"w": 16,
						"h": 26
					},
					"frame": {
						"x": 73,
						"y": 313,
						"w": 16,
						"h": 26
					}
				},
				{
					"filename": "adventurer-smrslt-03",
					"rotated": false,
					"trimmed": true,
					"sourceSize": {
						"w": 50,
						"h": 37
					},
					"spriteSourceSize": {
						"x": 11,
						"y": 13,
						"w": 26,
						"h": 17
					},
					"frame": {
						"x": 34,
						"y": 235,
						"w": 26,
						"h": 17
					}
				},
				{
					"filename": "adventurer-bow-00",
					"rotated": false,
					"trimmed": true,
					"sourceSize": {
						"w": 50,
						"h": 37
					},
					"spriteSourceSize": {
						"x": 16,
						"y": 10,
						"w": 20,
						"h": 26
					},
					"frame": {
						"x": 296,
						"y": 302,
						"w": 20,
						"h": 26
					}
				},
				{
					"filename": "adventurer-bow-jump-00",
					"rotated": false,
					"trimmed": true,
					"sourceSize": {
						"w": 50,
						"h": 37
					},
					"spriteSourceSize": {
						"x": 18,
						"y": 9,
						"w": 23,
						"h": 25
					},
					"frame": {
						"x": 293,
						"y": 130,
						"w": 23,
						"h": 25
					}
				},
				{
					"filename": "adventurer-bow-03",
					"rotated": false,
					"trimmed": true,
					"sourceSize": {
						"w": 50,
						"h": 37
					},
					"spriteSourceSize": {
						"x": 14,
						"y": 11,
						"w": 24,
						"h": 25
					},
					"frame": {
						"x": 91,
						"y": 313,
						"w": 24,
						"h": 25
					}
				},
				{
					"filename": "adventurer-run-05",
					"rotated": false,
					"trimmed": true,
					"sourceSize": {
						"w": 50,
						"h": 37
					},
					"spriteSourceSize": {
						"x": 16,
						"y": 11,
						"w": 20,
						"h": 25
					},
					"frame": {
						"x": 274,
						"y": 303,
						"w": 20,
						"h": 25
					}
				},
				{
					"filename": "adventurer-run-02",
					"rotated": false,
					"trimmed": true,
					"sourceSize": {
						"w": 50,
						"h": 37
					},
					"spriteSourceSize": {
						"x": 16,
						"y": 11,
						"w": 20,
						"h": 25
					},
					"frame": {
						"x": 295,
						"y": 157,
						"w": 20,
						"h": 25
					}
				},
				{
					"filename": "adventurer-bow-05",
					"rotated": false,
					"trimmed": true,
					"sourceSize": {
						"w": 50,
						"h": 37
					},
					"spriteSourceSize": {
						"x": 15,
						"y": 11,
						"w": 23,
						"h": 25
					},
					"frame": {
						"x": 117,
						"y": 313,
						"w": 23,
						"h": 25
					}
				},
				{
					"filename": "adventurer-items-01",
					"rotated": false,
					"trimmed": true,
					"sourceSize": {
						"w": 50,
						"h": 37
					},
					"spriteSourceSize": {
						"x": 16,
						"y": 11,
						"w": 21,
						"h": 25
					},
					"frame": {
						"x": 295,
						"y": 184,
						"w": 21,
						"h": 25
					}
				},
				{
					"filename": "adventurer-swrd-drw-00",
					"rotated": false,
					"trimmed": true,
					"sourceSize": {
						"w": 50,
						"h": 37
					},
					"spriteSourceSize": {
						"x": 15,
						"y": 11,
						"w": 18,
						"h": 25
					},
					"frame": {
						"x": 297,
						"y": 29,
						"w": 18,
						"h": 25
					}
				},
				{
					"filename": "adventurer-bow-jump-02",
					"rotated": false,
					"trimmed": true,
					"sourceSize": {
						"w": 50,
						"h": 37
					},
					"spriteSourceSize": {
						"x": 13,
						"y": 7,
						"w": 25,
						"h": 24
					},
					"frame": {
						"x": 142,
						"y": 313,
						"w": 25,
						"h": 24
					}
				},
				{
					"filename": "adventurer-swrd-shte-03",
					"rotated": false,
					"trimmed": true,
					"sourceSize": {
						"w": 50,
						"h": 37
					},
					"spriteSourceSize": {
						"x": 16,
						"y": 11,
						"w": 17,
						"h": 25
					},
					"frame": {
						"x": 297,
						"y": 88,
						"w": 17,
						"h": 25
					}
				},
				{
					"filename": "adventurer-cast-02",
					"rotated": false,
					"trimmed": true,
					"sourceSize": {
						"w": 50,
						"h": 37
					},
					"spriteSourceSize": {
						"x": 16,
						"y": 11,
						"w": 17,
						"h": 25
					},
					"frame": {
						"x": 297,
						"y": 211,
						"w": 17,
						"h": 25
					}
				},
				{
					"filename": "adventurer-cast-01",
					"rotated": false,
					"trimmed": true,
					"sourceSize": {
						"w": 50,
						"h": 37
					},
					"spriteSourceSize": {
						"x": 15,
						"y": 11,
						"w": 18,
						"h": 25
					},
					"frame": {
						"x": 297,
						"y": 238,
						"w": 18,
						"h": 25
					}
				},
				{
					"filename": "adventurer-attack1-01",
					"rotated": false,
					"trimmed": true,
					"sourceSize": {
						"w": 50,
						"h": 37
					},
					"spriteSourceSize": {
						"x": 8,
						"y": 16,
						"w": 25,
						"h": 20
					},
					"frame": {
						"x": 169,
						"y": 312,
						"w": 25,
						"h": 20
					}
				},
				{
					"filename": "adventurer-bow-01",
					"rotated": false,
					"trimmed": true,
					"sourceSize": {
						"w": 50,
						"h": 37
					},
					"spriteSourceSize": {
						"x": 15,
						"y": 11,
						"w": 22,
						"h": 25
					},
					"frame": {
						"x": 196,
						"y": 309,
						"w": 22,
						"h": 25
					}
				},
				{
					"filename": "adventurer-bow-02",
					"rotated": false,
					"trimmed": true,
					"sourceSize": {
						"w": 50,
						"h": 37
					},
					"spriteSourceSize": {
						"x": 17,
						"y": 12,
						"w": 24,
						"h": 24
					},
					"frame": {
						"x": 220,
						"y": 308,
						"w": 24,
						"h": 24
					}
				},
				{
					"filename": "adventurer-bow-jump-01",
					"rotated": false,
					"trimmed": true,
					"sourceSize": {
						"w": 50,
						"h": 37
					},
					"spriteSourceSize": {
						"x": 14,
						"y": 8,
						"w": 24,
						"h": 23
					},
					"frame": {
						"x": 246,
						"y": 305,
						"w": 24,
						"h": 23
					}
				},
				{
					"filename": "adventurer-jump-00",
					"rotated": false,
					"trimmed": true,
					"sourceSize": {
						"w": 50,
						"h": 37
					},
					"spriteSourceSize": {
						"x": 15,
						"y": 12,
						"w": 20,
						"h": 24
					},
					"frame": {
						"x": 318,
						"y": 1,
						"w": 20,
						"h": 24
					}
				},
				{
					"filename": "adventurer-crnr-clmb-03",
					"rotated": false,
					"trimmed": true,
					"sourceSize": {
						"w": 50,
						"h": 37
					},
					"spriteSourceSize": {
						"x": 21,
						"y": 6,
						"w": 14,
						"h": 24
					},
					"frame": {
						"x": 317,
						"y": 157,
						"w": 14,
						"h": 24
					}
				},
				{
					"filename": "adventurer-crnr-clmb-04",
					"rotated": false,
					"trimmed": true,
					"sourceSize": {
						"w": 50,
						"h": 37
					},
					"spriteSourceSize": {
						"x": 21,
						"y": 6,
						"w": 15,
						"h": 24
					},
					"frame": {
						"x": 316,
						"y": 211,
						"w": 15,
						"h": 24
					}
				},
				{
					"filename": "adventurer-hurt-00",
					"rotated": false,
					"trimmed": true,
					"sourceSize": {
						"w": 50,
						"h": 37
					},
					"spriteSourceSize": {
						"x": 16,
						"y": 12,
						"w": 21,
						"h": 24
					},
					"frame": {
						"x": 317,
						"y": 29,
						"w": 21,
						"h": 24
					}
				},
				{
					"filename": "adventurer-crnr-clmb-02",
					"rotated": false,
					"trimmed": true,
					"sourceSize": {
						"w": 50,
						"h": 37
					},
					"spriteSourceSize": {
						"x": 20,
						"y": 8,
						"w": 15,
						"h": 24
					},
					"frame": {
						"x": 318,
						"y": 183,
						"w": 15,
						"h": 24
					}
				},
				{
					"filename": "adventurer-die-00",
					"rotated": false,
					"trimmed": true,
					"sourceSize": {
						"w": 50,
						"h": 37
					},
					"spriteSourceSize": {
						"x": 16,
						"y": 12,
						"w": 21,
						"h": 24
					},
					"frame": {
						"x": 317,
						"y": 237,
						"w": 21,
						"h": 24
					}
				},
				{
					"filename": "adventurer-smrslt-01",
					"rotated": false,
					"trimmed": true,
					"sourceSize": {
						"w": 50,
						"h": 37
					},
					"spriteSourceSize": {
						"x": 14,
						"y": 10,
						"w": 24,
						"h": 17
					},
					"frame": {
						"x": 340,
						"y": 1,
						"w": 24,
						"h": 17
					}
				},
				{
					"filename": "adventurer-die-01",
					"rotated": false,
					"trimmed": true,
					"sourceSize": {
						"w": 50,
						"h": 37
					},
					"spriteSourceSize": {
						"x": 17,
						"y": 12,
						"w": 19,
						"h": 24
					},
					"frame": {
						"x": 333,
						"y": 209,
						"w": 19,
						"h": 24
					}
				},
				{
					"filename": "adventurer-hurt-01",
					"rotated": false,
					"trimmed": true,
					"sourceSize": {
						"w": 50,
						"h": 37
					},
					"spriteSourceSize": {
						"x": 17,
						"y": 12,
						"w": 19,
						"h": 24
					},
					"frame": {
						"x": 340,
						"y": 20,
						"w": 19,
						"h": 24
					}
				},
				{
					"filename": "adventurer-items-00",
					"rotated": false,
					"trimmed": true,
					"sourceSize": {
						"w": 50,
						"h": 37
					},
					"spriteSourceSize": {
						"x": 17,
						"y": 12,
						"w": 18,
						"h": 24
					},
					"frame": {
						"x": 340,
						"y": 235,
						"w": 18,
						"h": 24
					}
				},
				{
					"filename": "adventurer-die-02",
					"rotated": false,
					"trimmed": true,
					"sourceSize": {
						"w": 50,
						"h": 37
					},
					"spriteSourceSize": {
						"x": 15,
						"y": 12,
						"w": 19,
						"h": 24
					},
					"frame": {
						"x": 340,
						"y": 46,
						"w": 19,
						"h": 24
					}
				},
				{
					"filename": "adventurer-hurt-02",
					"rotated": false,
					"trimmed": true,
					"sourceSize": {
						"w": 50,
						"h": 37
					},
					"spriteSourceSize": {
						"x": 15,
						"y": 12,
						"w": 19,
						"h": 24
					},
					"frame": {
						"x": 318,
						"y": 55,
						"w": 19,
						"h": 24
					}
				},
				{
					"filename": "adventurer-jump-03",
					"rotated": false,
					"trimmed": true,
					"sourceSize": {
						"w": 50,
						"h": 37
					},
					"spriteSourceSize": {
						"x": 14,
						"y": 5,
						"w": 21,
						"h": 23
					},
					"frame": {
						"x": 340,
						"y": 261,
						"w": 21,
						"h": 23
					}
				},
				{
					"filename": "adventurer-crouch-01",
					"rotated": false,
					"trimmed": true,
					"sourceSize": {
						"w": 50,
						"h": 37
					},
					"spriteSourceSize": {
						"x": 15,
						"y": 14,
						"w": 20,
						"h": 22
					},
					"frame": {
						"x": 318,
						"y": 263,
						"w": 20,
						"h": 22
					}
				},
				{
					"filename": "adventurer-stand-02",
					"rotated": false,
					"trimmed": true,
					"sourceSize": {
						"w": 50,
						"h": 37
					},
					"spriteSourceSize": {
						"x": 15,
						"y": 19,
						"w": 22,
						"h": 17
					},
					"frame": {
						"x": 340,
						"y": 286,
						"w": 22,
						"h": 17
					}
				},
				{
					"filename": "adventurer-jump-01",
					"rotated": false,
					"trimmed": true,
					"sourceSize": {
						"w": 50,
						"h": 37
					},
					"spriteSourceSize": {
						"x": 15,
						"y": 14,
						"w": 20,
						"h": 22
					},
					"frame": {
						"x": 318,
						"y": 287,
						"w": 20,
						"h": 22
					}
				},
				{
					"filename": "adventurer-crouch-02",
					"rotated": false,
					"trimmed": true,
					"sourceSize": {
						"w": 50,
						"h": 37
					},
					"spriteSourceSize": {
						"x": 15,
						"y": 14,
						"w": 19,
						"h": 22
					},
					"frame": {
						"x": 340,
						"y": 305,
						"w": 19,
						"h": 22
					}
				},
				{
					"filename": "adventurer-die-03",
					"rotated": false,
					"trimmed": true,
					"sourceSize": {
						"w": 50,
						"h": 37
					},
					"spriteSourceSize": {
						"x": 16,
						"y": 14,
						"w": 22,
						"h": 22
					},
					"frame": {
						"x": 339,
						"y": 72,
						"w": 22,
						"h": 22
					}
				},
				{
					"filename": "adventurer-smrslt-02",
					"rotated": false,
					"trimmed": true,
					"sourceSize": {
						"w": 50,
						"h": 37
					},
					"spriteSourceSize": {
						"x": 20,
						"y": 10,
						"w": 18,
						"h": 21
					},
					"frame": {
						"x": 318,
						"y": 81,
						"w": 18,
						"h": 21
					}
				},
				{
					"filename": "adventurer-crouch-03",
					"rotated": false,
					"trimmed": true,
					"sourceSize": {
						"w": 50,
						"h": 37
					},
					"spriteSourceSize": {
						"x": 17,
						"y": 15,
						"w": 17,
						"h": 21
					},
					"frame": {
						"x": 318,
						"y": 311,
						"w": 17,
						"h": 21
					}
				},
				{
					"filename": "adventurer-smrslt-00",
					"rotated": false,
					"trimmed": true,
					"sourceSize": {
						"w": 50,
						"h": 37
					},
					"spriteSourceSize": {
						"x": 18,
						"y": 7,
						"w": 15,
						"h": 21
					},
					"frame": {
						"x": 237,
						"y": 280,
						"w": 15,
						"h": 21
					}
				},
				{
					"filename": "adventurer-crouch-00",
					"rotated": false,
					"trimmed": true,
					"sourceSize": {
						"w": 50,
						"h": 37
					},
					"spriteSourceSize": {
						"x": 16,
						"y": 15,
						"w": 19,
						"h": 21
					},
					"frame": {
						"x": 316,
						"y": 104,
						"w": 19,
						"h": 21
					}
				},
				{
					"filename": "adventurer-die-06",
					"rotated": false,
					"trimmed": true,
					"sourceSize": {
						"w": 50,
						"h": 37
					},
					"spriteSourceSize": {
						"x": 18,
						"y": 18,
						"w": 18,
						"h": 18
					},
					"frame": {
						"x": 275,
						"y": 193,
						"w": 18,
						"h": 18
					}
				},
				{
					"filename": "adventurer-die-04",
					"rotated": false,
					"trimmed": true,
					"sourceSize": {
						"w": 50,
						"h": 37
					},
					"spriteSourceSize": {
						"x": 18,
						"y": 18,
						"w": 18,
						"h": 18
					},
					"frame": {
						"x": 338,
						"y": 96,
						"w": 18,
						"h": 18
					}
				},
				{
					"filename": "adventurer-die-05",
					"rotated": false,
					"trimmed": true,
					"sourceSize": {
						"w": 50,
						"h": 37
					},
					"spriteSourceSize": {
						"x": 21,
						"y": 19,
						"w": 15,
						"h": 17
					},
					"frame": {
						"x": 318,
						"y": 127,
						"w": 15,
						"h": 17
					}
				}
			]
		}
	],
	"meta": {
		"app": "http://free-tex-packer.com",
		"version": "0.6.6"
	}
}